LICENSE
MANIFEST.in
README.md
setup.py
leech_tentacle/__init__.py
leech_tentacle/extraction.py
leech_tentacle/extraction_config.py
leech_tentacle/extraction_template.py
leech_tentacle/extractors.py
leech_tentacle/processors.py
leech_tentacle/troubles.py
leech_tentacle.egg-info/PKG-INFO
leech_tentacle.egg-info/SOURCES.txt
leech_tentacle.egg-info/dependency_links.txt
leech_tentacle.egg-info/requires.txt
leech_tentacle.egg-info/top_level.txt