Metadata-Version: 2.1
Name: leech-tentacle
Version: 0.0.1
Summary: the basic modules used to design a new tentacle for the Algernon Leech platform
Home-page: https://github.com/AlgernonSolutions/leech_tentacle
Author: algernon_solutions/jcubeta
Author-email: jcubeta@algernon.solutions
License: GNU Affero General Public License v3.0
Platform: UNKNOWN
Classifier: Programming Language :: Python :: 3
Classifier: License :: OSI Approved :: GNU Affero General Public License v3
Classifier: Operating System :: OS Independent
Requires-Python: >=3.8.0
